cleanlyze/__init__.py
cleanlyze/cleaning.py
cleanlyze/dataAgregation.py
cleanlyze/dataEncoding.py
cleanlyze/exportImport.py
cleanlyze/timeSeriesProcessing.py
cleanlyze/transformation.py
cleanlyze/utility.py
cleanlyze/visualisation.py
Cleanlyze-0.1.dist-info/METADATA
Cleanlyze-0.1.dist-info/WHEEL
Cleanlyze-0.1.dist-info/top_level.txt
Cleanlyze-0.1.dist-info/RECORD
